odoo/addons/purchase_tier_validation/README.rst
odoo/addons/purchase_tier_validation/__init__.py
odoo/addons/purchase_tier_validation/__manifest__.py
odoo/addons/purchase_tier_validation/i18n/es.po
odoo/addons/purchase_tier_validation/i18n/fr.po
odoo/addons/purchase_tier_validation/i18n/it.po
odoo/addons/purchase_tier_validation/i18n/purchase_tier_validation.pot
odoo/addons/purchase_tier_validation/i18n/zh_CN.po
odoo/addons/purchase_tier_validation/models/__init__.py
odoo/addons/purchase_tier_validation/models/purchase_order.py
odoo/addons/purchase_tier_validation/models/tier_definition.py
odoo/addons/purchase_tier_validation/readme/CONFIGURE.rst
odoo/addons/purchase_tier_validation/readme/CONTRIBUTORS.rst
odoo/addons/purchase_tier_validation/readme/DESCRIPTION.rst
odoo/addons/purchase_tier_validation/readme/INSTALL.rst
odoo/addons/purchase_tier_validation/readme/USAGE.rst
odoo/addons/purchase_tier_validation/static/description/icon.png
odoo/addons/purchase_tier_validation/static/description/index.html
odoo/addons/purchase_tier_validation/tests/__init__.py
odoo/addons/purchase_tier_validation/tests/test_tier_validation.py
odoo/addons/purchase_tier_validation/views/purchase_order_view.xml
odoo14_addon_purchase_tier_validation-14.0.2.1.0.dist-info/METADATA
odoo14_addon_purchase_tier_validation-14.0.2.1.0.dist-info/WHEEL
odoo14_addon_purchase_tier_validation-14.0.2.1.0.dist-info/top_level.txt
odoo14_addon_purchase_tier_validation-14.0.2.1.0.dist-info/RECORD
